simple_guard/__init__.py
simple_guard/assistant.py
simple_guard/guards.py
simple_guard/rules.py
simple_guard-0.1.11.dist-info/LICENSE
simple_guard-0.1.11.dist-info/METADATA
simple_guard-0.1.11.dist-info/WHEEL
simple_guard-0.1.11.dist-info/RECORD
