Metadata-Version: 2.1
Name: simple-guard
Version: 0.1.11
Summary: A Lightweight & Extensible OpenAI Wrapper for Simple Guardrails
License: Apache-2.0
Author: Bastiaan Witte
Author-email: bastiaan@foodticket.nl
Requires-Python: >=3.10,<4.0
Classifier: License :: OSI Approved :: Apache Software License
Classifier: Programming Language :: Python :: 3
Classifier: Programming Language :: Python :: 3.10
Classifier: Programming Language :: Python :: 3.11
Classifier: Programming Language :: Python :: 3.12
Classifier: Programming Language :: Python :: 3.13
Requires-Dist: openai (>=1.50,<2.0)
Requires-Dist: presidio-analyzer (>=2.2.351,<3.0.0)
Requires-Dist: presidio-anonymizer (>=2.2.351,<3.0.0)
Requires-Dist: python-dotenv (>=1.0.0,<2.0.0)
